Mainlab/__init__.py
Mainlab/myfunctions.py
Mainlab-0.1.0.dist-info/METADATA
Mainlab-0.1.0.dist-info/WHEEL
Mainlab-0.1.0.dist-info/top_level.txt
Mainlab-0.1.0.dist-info/RECORD
